orgmunge/__init__.py
orgmunge/classes.py
orgmunge/lexer.py
orgmunge/parser.out
orgmunge/parser.py
orgmunge/parsetab.py
orgmunge/todos.json
orgmunge-0.3.1.dist-info/LICENSE
orgmunge-0.3.1.dist-info/METADATA
orgmunge-0.3.1.dist-info/WHEEL
orgmunge-0.3.1.dist-info/RECORD
