Metadata-Version: 2.3
Name: orgmunge
Version: 0.3.1
Summary: Programmatically modify Orgmode documents
License: MIT
Author: durableOne 
Author-email: era31asj@gmail.com
Requires-Python: >=3.10,<4.0
Classifier: License :: OSI Approved :: MIT License
Classifier: Programming Language :: Python :: 3
Classifier: Programming Language :: Python :: 3.10
Classifier: Programming Language :: Python :: 3.11
Classifier: Programming Language :: Python :: 3.12
Classifier: Programming Language :: Python :: 3.13
Requires-Dist: ply (>=3.11,<4.0)
